tempo/__init__.py
tempo/interpol.py
tempo/intervals.py
tempo/io.py
tempo/ml.py
tempo/resample.py
tempo/tsdf.py
tempo/utils.py
dbl_tempo-0.1.30.dist-info/METADATA
dbl_tempo-0.1.30.dist-info/WHEEL
dbl_tempo-0.1.30.dist-info/top_level.txt
dbl_tempo-0.1.30.dist-info/RECORD
