Metadata-Version: 2.4
Name: dbl-tempo
Version: 0.1.30
Summary: Tempo is timeseries manipulation for Spark. This project builds upon the capabilities of PySpark to provide a suite of abstractions and functions that make operations on timeseries data easier and highly scalable.
Home-page: https://databrickslabs.github.io/tempo/
Author: Ricardo Portilla, Tristan Nixon, Max Thone, Sonali Guleria
Author-email: Lorin Dawson <lorin.dawson@databricks.com>, Kevin Wang <k.wang@databricks.com>, Hector Bustamante <hector.bustamante@databricks.com>
License-Expression: MIT
Project-URL: Documentation, https://databrickslabs.github.io/tempo/
Project-URL: Issues, https://github.com/databrickslabs/tempo/issues
Project-URL: Source, https://github.com/databrickslabs/tempo
Classifier: Development Status :: 4 - Beta
Classifier: Programming Language :: Python
Classifier: Programming Language :: Python :: 3.9
Classifier: Programming Language :: Python :: 3.10
Classifier: Programming Language :: Python :: 3.11
Classifier: Programming Language :: Python :: 3.12
Classifier: Programming Language :: Python :: Implementation :: CPython
Classifier: Programming Language :: Python :: Implementation :: PyPy
Requires-Python: >=3.9
Dynamic: author
Dynamic: home-page
